[
  {
    "seed": 0,
    "bad_frac": 0.75,
    "transition_counts": {
      "positive": 160,
      "negative": 226,
      "unlabeled": 3349,
      "unlabeled_hidden_good": 1795,
      "unlabeled_hidden_bad": 1554,
      "selected_unlabeled": 1795,
      "selected_unlabeled_hidden_good": 1795,
      "selected_unlabeled_hidden_bad": 0
    },
    "selected_unlabeled_demos": {
      "count": 45,
      "hidden_good": 45,
      "hidden_bad": 0,
      "top_unlabeled_frac": 0.25,
      "score_mean": 0.7281426191329956
    },
    "classifier": {
      "pos_prob_mean": 0.9959663152694702,
      "neg_prob_mean": 0.005557355936616659,
      "unlabeled_prob_mean": 0.3946870267391205,
      "unlabeled_hidden_good_prob_mean": 0.7280774116516113,
      "unlabeled_hidden_bad_prob_mean": 0.00959333498030901,
      "labeled_accuracy": 1.0
    },
    "histories": {
      "state_action_classifier": [
        {
          "step": 1,
          "loss": 1.3638877868652344
        },
        {
          "step": 500,
          "loss": 0.10028153657913208
        },
        {
          "step": 1000,
          "loss": 0.04791279137134552
        },
        {
          "step": 1500,
          "loss": 0.033760327845811844
        },
        {
          "step": 2000,
          "loss": 0.014242530800402164
        },
        {
          "step": 2500,
          "loss": 0.008503968827426434
        }
      ],
      "bc_positive_prefix": [
        {
          "step": 1,
          "loss": 0.005723210051655769
        },
        {
          "step": 1200,
          "loss": 1.1200097105756868e-05
        },
        {
          "step": 2400,
          "loss": 1.0131566341442522e-05
        },
        {
          "step": 3600,
          "loss": 9.63846377999289e-06
        },
        {
          "step": 4800,
          "loss": 9.210603820974939e-06
        },
        {
          "step": 6000,
          "loss": 7.655658009753097e-06
        }
      ],
      "bc_pos_unlabeled": [
        {
          "step": 1,
          "loss": 0.0054610539227724075
        },
        {
          "step": 1200,
          "loss": 9.530016541248187e-05
        },
        {
          "step": 2400,
          "loss": 0.00010229826875729486
        },
        {
          "step": 3600,
          "loss": 8.559564594179392e-05
        },
        {
          "step": 4800,
          "loss": 9.051901724888012e-05
        },
        {
          "step": 6000,
          "loss": 8.856658678269014e-05
        }
      ],
      "bc_all": [
        {
          "step": 1,
          "loss": 0.03100634552538395
        },
        {
          "step": 1200,
          "loss": 0.00010174766066484153
        },
        {
          "step": 2400,
          "loss": 8.819586219033226e-05
        },
        {
          "step": 3600,
          "loss": 8.44389942358248e-05
        },
        {
          "step": 4800,
          "loss": 9.297068027080968e-05
        },
        {
          "step": 6000,
          "loss": 8.762566721998155e-05
        }
      ],
      "weighted_bc_state_action": [
        {
          "step": 1,
          "loss": 0.004089570604264736
        },
        {
          "step": 1200,
          "loss": 9.701876115286723e-05
        },
        {
          "step": 2400,
          "loss": 8.505093137500808e-05
        },
        {
          "step": 3600,
          "loss": 9.117250010604039e-05
        },
        {
          "step": 4800,
          "loss": 9.65591607382521e-05
        },
        {
          "step": 6000,
          "loss": 6.66218766127713e-05
        }
      ],
      "tri_signal_top_demo_bc": [
        {
          "step": 1,
          "loss": 0.014987427741289139
        },
        {
          "step": 1200,
          "loss": 8.99989390745759e-05
        },
        {
          "step": 2400,
          "loss": 7.98265464254655e-05
        },
        {
          "step": 3600,
          "loss": 7.843995990697294e-05
        },
        {
          "step": 4800,
          "loss": 7.875631126808003e-05
        },
        {
          "step": 6000,
          "loss": 7.861397898523137e-05
        }
      ],
      "oracle_good_bc": [
        {
          "step": 1,
          "loss": 0.02429579570889473
        },
        {
          "step": 1200,
          "loss": 8.238309237640351e-05
        },
        {
          "step": 2400,
          "loss": 7.986289710970595e-05
        },
        {
          "step": 3600,
          "loss": 7.742687739664689e-05
        },
        {
          "step": 4800,
          "loss": 7.649834151379764e-05
        },
        {
          "step": 6000,
          "loss": 6.461548764491454e-05
        }
      ]
    }
  },
  {
    "seed": 1,
    "bad_frac": 0.75,
    "transition_counts": {
      "positive": 160,
      "negative": 230,
      "unlabeled": 3168,
      "unlabeled_hidden_good": 1515,
      "unlabeled_hidden_bad": 1653,
      "selected_unlabeled": 1603,
      "selected_unlabeled_hidden_good": 1515,
      "selected_unlabeled_hidden_bad": 88
    },
    "selected_unlabeled_demos": {
      "count": 45,
      "hidden_good": 38,
      "hidden_bad": 7,
      "top_unlabeled_frac": 0.25,
      "score_mean": 0.5751076576610407
    },
    "classifier": {
      "pos_prob_mean": 0.9947016835212708,
      "neg_prob_mean": 0.004829208832234144,
      "unlabeled_prob_mean": 0.3229024410247803,
      "unlabeled_hidden_good_prob_mean": 0.6685294508934021,
      "unlabeled_hidden_bad_prob_mean": 0.006129920016974211,
      "labeled_accuracy": 1.0
    },
    "histories": {
      "state_action_classifier": [
        {
          "step": 1,
          "loss": 1.3792072534561157
        },
        {
          "step": 500,
          "loss": 0.08460252732038498
        },
        {
          "step": 1000,
          "loss": 0.0695708692073822
        },
        {
          "step": 1500,
          "loss": 0.031020676717162132
        },
        {
          "step": 2000,
          "loss": 0.02181827276945114
        },
        {
          "step": 2500,
          "loss": 0.015285284258425236
        }
      ],
      "bc_positive_prefix": [
        {
          "step": 1,
          "loss": 0.010530941188335419
        },
        {
          "step": 1200,
          "loss": 9.625927305023652e-06
        },
        {
          "step": 2400,
          "loss": 8.611834346083924e-06
        },
        {
          "step": 3600,
          "loss": 7.323046247620368e-06
        },
        {
          "step": 4800,
          "loss": 9.570903785061091e-06
        },
        {
          "step": 6000,
          "loss": 8.89193506736774e-06
        }
      ],
      "bc_pos_unlabeled": [
        {
          "step": 1,
          "loss": 0.025110451504588127
        },
        {
          "step": 1200,
          "loss": 0.00010043384827440605
        },
        {
          "step": 2400,
          "loss": 9.54043644014746e-05
        },
        {
          "step": 3600,
          "loss": 9.575353033142164e-05
        },
        {
          "step": 4800,
          "loss": 0.00010228257451672107
        },
        {
          "step": 6000,
          "loss": 0.0001002288845484145
        }
      ],
      "bc_all": [
        {
          "step": 1,
          "loss": 0.007660464849323034
        },
        {
          "step": 1200,
          "loss": 8.680867904331535e-05
        },
        {
          "step": 2400,
          "loss": 9.705269621917978e-05
        },
        {
          "step": 3600,
          "loss": 8.06103489594534e-05
        },
        {
          "step": 4800,
          "loss": 9.22716353670694e-05
        },
        {
          "step": 6000,
          "loss": 9.422450239071622e-05
        }
      ],
      "weighted_bc_state_action": [
        {
          "step": 1,
          "loss": 0.016065631061792374
        },
        {
          "step": 1200,
          "loss": 9.33836490730755e-05
        },
        {
          "step": 2400,
          "loss": 0.00011468256707303226
        },
        {
          "step": 3600,
          "loss": 0.00010785352787934244
        },
        {
          "step": 4800,
          "loss": 8.138758857967332e-05
        },
        {
          "step": 6000,
          "loss": 8.820262155495584e-05
        }
      ],
      "tri_signal_top_demo_bc": [
        {
          "step": 1,
          "loss": 0.028207678347826004
        },
        {
          "step": 1200,
          "loss": 0.00010839621245395392
        },
        {
          "step": 2400,
          "loss": 8.711367263458669e-05
        },
        {
          "step": 3600,
          "loss": 9.323807898908854e-05
        },
        {
          "step": 4800,
          "loss": 8.114460797514766e-05
        },
        {
          "step": 6000,
          "loss": 9.09468435565941e-05
        }
      ],
      "oracle_good_bc": [
        {
          "step": 1,
          "loss": 0.016992544755339622
        },
        {
          "step": 1200,
          "loss": 9.104370110435411e-05
        },
        {
          "step": 2400,
          "loss": 8.227272337535396e-05
        },
        {
          "step": 3600,
          "loss": 9.879874414764345e-05
        },
        {
          "step": 4800,
          "loss": 7.302826998056844e-05
        },
        {
          "step": 6000,
          "loss": 8.186740888049826e-05
        }
      ]
    }
  },
  {
    "seed": 2,
    "bad_frac": 0.75,
    "transition_counts": {
      "positive": 160,
      "negative": 231,
      "unlabeled": 3589,
      "unlabeled_hidden_good": 2131,
      "unlabeled_hidden_bad": 1458,
      "selected_unlabeled": 1774,
      "selected_unlabeled_hidden_good": 1774,
      "selected_unlabeled_hidden_bad": 0
    },
    "selected_unlabeled_demos": {
      "count": 45,
      "hidden_good": 45,
      "hidden_bad": 0,
      "top_unlabeled_frac": 0.25,
      "score_mean": 0.7158315817515055
    },
    "classifier": {
      "pos_prob_mean": 0.9945006370544434,
      "neg_prob_mean": 0.005148258991539478,
      "unlabeled_prob_mean": 0.4265533983707428,
      "unlabeled_hidden_good_prob_mean": 0.7115970849990845,
      "unlabeled_hidden_bad_prob_mean": 0.009936116635799408,
      "labeled_accuracy": 1.0
    },
    "histories": {
      "state_action_classifier": [
        {
          "step": 1,
          "loss": 1.3847992420196533
        },
        {
          "step": 500,
          "loss": 0.09933365881443024
        },
        {
          "step": 1000,
          "loss": 0.06517717242240906
        },
        {
          "step": 1500,
          "loss": 0.03177409619092941
        },
        {
          "step": 2000,
          "loss": 0.019928131252527237
        },
        {
          "step": 2500,
          "loss": 0.013734007254242897
        }
      ],
      "bc_positive_prefix": [
        {
          "step": 1,
          "loss": 0.002433351706713438
        },
        {
          "step": 1200,
          "loss": 1.0560058399278205e-05
        },
        {
          "step": 2400,
          "loss": 9.939574738382362e-06
        },
        {
          "step": 3600,
          "loss": 9.93492085399339e-06
        },
        {
          "step": 4800,
          "loss": 8.694034477230161e-06
        },
        {
          "step": 6000,
          "loss": 9.622028301237151e-06
        }
      ],
      "bc_pos_unlabeled": [
        {
          "step": 1,
          "loss": 0.006984401028603315
        },
        {
          "step": 1200,
          "loss": 0.0001020548224914819
        },
        {
          "step": 2400,
          "loss": 9.399653936270624e-05
        },
        {
          "step": 3600,
          "loss": 8.454541966784745e-05
        },
        {
          "step": 4800,
          "loss": 0.00010110294533660635
        },
        {
          "step": 6000,
          "loss": 9.295636846218258e-05
        }
      ],
      "bc_all": [
        {
          "step": 1,
          "loss": 0.012602124363183975
        },
        {
          "step": 1200,
          "loss": 0.00010547100100666285
        },
        {
          "step": 2400,
          "loss": 9.110327664529905e-05
        },
        {
          "step": 3600,
          "loss": 9.037858399096876e-05
        },
        {
          "step": 4800,
          "loss": 8.501071715727448e-05
        },
        {
          "step": 6000,
          "loss": 8.762531797401607e-05
        }
      ],
      "weighted_bc_state_action": [
        {
          "step": 1,
          "loss": 0.012885581701993942
        },
        {
          "step": 1200,
          "loss": 0.00012054768012603745
        },
        {
          "step": 2400,
          "loss": 0.00010576029308140278
        },
        {
          "step": 3600,
          "loss": 8.93403121153824e-05
        },
        {
          "step": 4800,
          "loss": 7.621815166203305e-05
        },
        {
          "step": 6000,
          "loss": 9.263156243832782e-05
        }
      ],
      "tri_signal_top_demo_bc": [
        {
          "step": 1,
          "loss": 0.01374930702149868
        },
        {
          "step": 1200,
          "loss": 7.563884719274938e-05
        },
        {
          "step": 2400,
          "loss": 7.738752174191177e-05
        },
        {
          "step": 3600,
          "loss": 7.512798038078472e-05
        },
        {
          "step": 4800,
          "loss": 6.920066516613588e-05
        },
        {
          "step": 6000,
          "loss": 6.826491880929098e-05
        }
      ],
      "oracle_good_bc": [
        {
          "step": 1,
          "loss": 0.012311587110161781
        },
        {
          "step": 1200,
          "loss": 7.682717841817066e-05
        },
        {
          "step": 2400,
          "loss": 8.206011989386752e-05
        },
        {
          "step": 3600,
          "loss": 7.924655074020848e-05
        },
        {
          "step": 4800,
          "loss": 7.521230145357549e-05
        },
        {
          "step": 6000,
          "loss": 7.190831820480525e-05
        }
      ]
    }
  },
  {
    "seed": 0,
    "bad_frac": 0.9,
    "transition_counts": {
      "positive": 160,
      "negative": 226,
      "unlabeled": 2627,
      "unlabeled_hidden_good": 760,
      "unlabeled_hidden_bad": 1867,
      "selected_unlabeled": 1067,
      "selected_unlabeled_hidden_good": 760,
      "selected_unlabeled_hidden_bad": 307
    },
    "selected_unlabeled_demos": {
      "count": 45,
      "hidden_good": 19,
      "hidden_bad": 26,
      "top_unlabeled_frac": 0.25,
      "score_mean": 0.325836781764196
    },
    "classifier": {
      "pos_prob_mean": 0.9961000680923462,
      "neg_prob_mean": 0.0053664096631109715,
      "unlabeled_prob_mean": 0.2164064347743988,
      "unlabeled_hidden_good_prob_mean": 0.7279714345932007,
      "unlabeled_hidden_bad_prob_mean": 0.008163600228726864,
      "labeled_accuracy": 1.0
    },
    "histories": {
      "state_action_classifier": [
        {
          "step": 1,
          "loss": 1.3650035858154297
        },
        {
          "step": 500,
          "loss": 0.09752430021762848
        },
        {
          "step": 1000,
          "loss": 0.04675963521003723
        },
        {
          "step": 1500,
          "loss": 0.034223154187202454
        },
        {
          "step": 2000,
          "loss": 0.013911176472902298
        },
        {
          "step": 2500,
          "loss": 0.008156032301485538
        }
      ],
      "bc_positive_prefix": [
        {
          "step": 1,
          "loss": 0.015706965699791908
        },
        {
          "step": 1200,
          "loss": 1.1675930181809235e-05
        },
        {
          "step": 2400,
          "loss": 1.0743591701611876e-05
        },
        {
          "step": 3600,
          "loss": 1.0761459634522907e-05
        },
        {
          "step": 4800,
          "loss": 1.1763619113480672e-05
        },
        {
          "step": 6000,
          "loss": 8.459680429950822e-06
        }
      ],
      "bc_pos_unlabeled": [
        {
          "step": 1,
          "loss": 0.00620610173791647
        },
        {
          "step": 1200,
          "loss": 9.134290303336456e-05
        },
        {
          "step": 2400,
          "loss": 0.0001002527424134314
        },
        {
          "step": 3600,
          "loss": 9.353788482258096e-05
        },
        {
          "step": 4800,
          "loss": 8.232140680775046e-05
        },
        {
          "step": 6000,
          "loss": 8.80705556483008e-05
        }
      ],
      "bc_all": [
        {
          "step": 1,
          "loss": 0.031370922923088074
        },
        {
          "step": 1200,
          "loss": 9.52884802245535e-05
        },
        {
          "step": 2400,
          "loss": 7.843364437576383e-05
        },
        {
          "step": 3600,
          "loss": 7.951453153509647e-05
        },
        {
          "step": 4800,
          "loss": 8.875105413608253e-05
        },
        {
          "step": 6000,
          "loss": 8.274512947537005e-05
        }
      ],
      "weighted_bc_state_action": [
        {
          "step": 1,
          "loss": 0.008341914974153042
        },
        {
          "step": 1200,
          "loss": 9.300433885073289e-05
        },
        {
          "step": 2400,
          "loss": 9.593296999810264e-05
        },
        {
          "step": 3600,
          "loss": 0.00010188483429374173
        },
        {
          "step": 4800,
          "loss": 0.00013189055607654154
        },
        {
          "step": 6000,
          "loss": 0.00010759565338958055
        }
      ],
      "tri_signal_top_demo_bc": [
        {
          "step": 1,
          "loss": 0.019557414576411247
        },
        {
          "step": 1200,
          "loss": 0.00010895609011640772
        },
        {
          "step": 2400,
          "loss": 9.40100071602501e-05
        },
        {
          "step": 3600,
          "loss": 7.500778156099841e-05
        },
        {
          "step": 4800,
          "loss": 8.308481483254582e-05
        },
        {
          "step": 6000,
          "loss": 8.534851076547056e-05
        }
      ],
      "oracle_good_bc": [
        {
          "step": 1,
          "loss": 0.042388346046209335
        },
        {
          "step": 1200,
          "loss": 8.107535541057587e-05
        },
        {
          "step": 2400,
          "loss": 8.301546768052503e-05
        },
        {
          "step": 3600,
          "loss": 8.525099838152528e-05
        },
        {
          "step": 4800,
          "loss": 7.223976717796177e-05
        },
        {
          "step": 6000,
          "loss": 0.00010346037015551701
        }
      ]
    }
  },
  {
    "seed": 1,
    "bad_frac": 0.9,
    "transition_counts": {
      "positive": 160,
      "negative": 230,
      "unlabeled": 2590,
      "unlabeled_hidden_good": 717,
      "unlabeled_hidden_bad": 1873,
      "selected_unlabeled": 1035,
      "selected_unlabeled_hidden_good": 717,
      "selected_unlabeled_hidden_bad": 318
    },
    "selected_unlabeled_demos": {
      "count": 45,
      "hidden_good": 18,
      "hidden_bad": 27,
      "top_unlabeled_frac": 0.25,
      "score_mean": 0.27877373644668196
    },
    "classifier": {
      "pos_prob_mean": 0.9947681427001953,
      "neg_prob_mean": 0.004785643424838781,
      "unlabeled_prob_mean": 0.1872781366109848,
      "unlabeled_hidden_good_prob_mean": 0.6635884642601013,
      "unlabeled_hidden_bad_prob_mean": 0.004942600149661303,
      "labeled_accuracy": 1.0
    },
    "histories": {
      "state_action_classifier": [
        {
          "step": 1,
          "loss": 1.39878511428833
        },
        {
          "step": 500,
          "loss": 0.08491980284452438
        },
        {
          "step": 1000,
          "loss": 0.07292810827493668
        },
        {
          "step": 1500,
          "loss": 0.03172852098941803
        },
        {
          "step": 2000,
          "loss": 0.021788565441966057
        },
        {
          "step": 2500,
          "loss": 0.01496407762169838
        }
      ],
      "bc_positive_prefix": [
        {
          "step": 1,
          "loss": 0.011525827459990978
        },
        {
          "step": 1200,
          "loss": 9.7937509053736e-06
        },
        {
          "step": 2400,
          "loss": 8.77098773344187e-06
        },
        {
          "step": 3600,
          "loss": 7.484851266781334e-06
        },
        {
          "step": 4800,
          "loss": 8.965875167632475e-06
        },
        {
          "step": 6000,
          "loss": 8.048747076827567e-06
        }
      ],
      "bc_pos_unlabeled": [
        {
          "step": 1,
          "loss": 0.02852454222738743
        },
        {
          "step": 1200,
          "loss": 8.209820225602016e-05
        },
        {
          "step": 2400,
          "loss": 9.157219028566033e-05
        },
        {
          "step": 3600,
          "loss": 9.339090320281684e-05
        },
        {
          "step": 4800,
          "loss": 9.165448136627674e-05
        },
        {
          "step": 6000,
          "loss": 8.521396375726908e-05
        }
      ],
      "bc_all": [
        {
          "step": 1,
          "loss": 0.008201352320611477
        },
        {
          "step": 1200,
          "loss": 8.955703378887847e-05
        },
        {
          "step": 2400,
          "loss": 8.558046101825312e-05
        },
        {
          "step": 3600,
          "loss": 8.019274537218735e-05
        },
        {
          "step": 4800,
          "loss": 9.185979433823377e-05
        },
        {
          "step": 6000,
          "loss": 7.727772026555613e-05
        }
      ],
      "weighted_bc_state_action": [
        {
          "step": 1,
          "loss": 0.027087213471531868
        },
        {
          "step": 1200,
          "loss": 0.00011217573774047196
        },
        {
          "step": 2400,
          "loss": 9.205009700963274e-05
        },
        {
          "step": 3600,
          "loss": 8.727373642614111e-05
        },
        {
          "step": 4800,
          "loss": 8.81166779436171e-05
        },
        {
          "step": 6000,
          "loss": 0.00011098410323029384
        }
      ],
      "tri_signal_top_demo_bc": [
        {
          "step": 1,
          "loss": 0.0338418148458004
        },
        {
          "step": 1200,
          "loss": 0.00010373302939115092
        },
        {
          "step": 2400,
          "loss": 9.53226481215097e-05
        },
        {
          "step": 3600,
          "loss": 7.722208101768047e-05
        },
        {
          "step": 4800,
          "loss": 8.793499728199095e-05
        },
        {
          "step": 6000,
          "loss": 8.464331040158868e-05
        }
      ],
      "oracle_good_bc": [
        {
          "step": 1,
          "loss": 0.026837822049856186
        },
        {
          "step": 1200,
          "loss": 7.383045158348978e-05
        },
        {
          "step": 2400,
          "loss": 8.109539339784533e-05
        },
        {
          "step": 3600,
          "loss": 9.698056237539276e-05
        },
        {
          "step": 4800,
          "loss": 8.492764754919335e-05
        },
        {
          "step": 6000,
          "loss": 7.753480167593807e-05
        }
      ]
    }
  },
  {
    "seed": 2,
    "bad_frac": 0.9,
    "transition_counts": {
      "positive": 160,
      "negative": 231,
      "unlabeled": 2679,
      "unlabeled_hidden_good": 838,
      "unlabeled_hidden_bad": 1841,
      "selected_unlabeled": 1111,
      "selected_unlabeled_hidden_good": 838,
      "selected_unlabeled_hidden_bad": 273
    },
    "selected_unlabeled_demos": {
      "count": 45,
      "hidden_good": 21,
      "hidden_bad": 24,
      "top_unlabeled_frac": 0.25,
      "score_mean": 0.3575013148287932
    },
    "classifier": {
      "pos_prob_mean": 0.994864284992218,
      "neg_prob_mean": 0.004784278571605682,
      "unlabeled_prob_mean": 0.23092877864837646,
      "unlabeled_hidden_good_prob_mean": 0.7202773094177246,
      "unlabeled_hidden_bad_prob_mean": 0.008183463476598263,
      "labeled_accuracy": 1.0
    },
    "histories": {
      "state_action_classifier": [
        {
          "step": 1,
          "loss": 1.388082504272461
        },
        {
          "step": 500,
          "loss": 0.09892295300960541
        },
        {
          "step": 1000,
          "loss": 0.06357177346944809
        },
        {
          "step": 1500,
          "loss": 0.031113408505916595
        },
        {
          "step": 2000,
          "loss": 0.019001757726073265
        },
        {
          "step": 2500,
          "loss": 0.012822285294532776
        }
      ],
      "bc_positive_prefix": [
        {
          "step": 1,
          "loss": 0.005338648334145546
        },
        {
          "step": 1200,
          "loss": 1.0901906534854788e-05
        },
        {
          "step": 2400,
          "loss": 9.708762263471726e-06
        },
        {
          "step": 3600,
          "loss": 9.979113201552536e-06
        },
        {
          "step": 4800,
          "loss": 8.480303222313523e-06
        },
        {
          "step": 6000,
          "loss": 1.0063303307106253e-05
        }
      ],
      "bc_pos_unlabeled": [
        {
          "step": 1,
          "loss": 0.00914836023002863
        },
        {
          "step": 1200,
          "loss": 8.975584205472842e-05
        },
        {
          "step": 2400,
          "loss": 9.457614942220971e-05
        },
        {
          "step": 3600,
          "loss": 9.762696572579443e-05
        },
        {
          "step": 4800,
          "loss": 8.22480142232962e-05
        },
        {
          "step": 6000,
          "loss": 9.05486595002003e-05
        }
      ],
      "bc_all": [
        {
          "step": 1,
          "loss": 0.012158737517893314
        },
        {
          "step": 1200,
          "loss": 8.937798702390864e-05
        },
        {
          "step": 2400,
          "loss": 8.906233415473253e-05
        },
        {
          "step": 3600,
          "loss": 8.991138747660443e-05
        },
        {
          "step": 4800,
          "loss": 8.904111746232957e-05
        },
        {
          "step": 6000,
          "loss": 8.120083657559007e-05
        }
      ],
      "weighted_bc_state_action": [
        {
          "step": 1,
          "loss": 0.019592957571148872
        },
        {
          "step": 1200,
          "loss": 8.610374788986519e-05
        },
        {
          "step": 2400,
          "loss": 8.072367927525192e-05
        },
        {
          "step": 3600,
          "loss": 0.00011053228081436828
        },
        {
          "step": 4800,
          "loss": 0.00012909556971862912
        },
        {
          "step": 6000,
          "loss": 0.0001133824116550386
        }
      ],
      "tri_signal_top_demo_bc": [
        {
          "step": 1,
          "loss": 0.020308155566453934
        },
        {
          "step": 1200,
          "loss": 9.053919347934425e-05
        },
        {
          "step": 2400,
          "loss": 8.201908349292353e-05
        },
        {
          "step": 3600,
          "loss": 7.999717490747571e-05
        },
        {
          "step": 4800,
          "loss": 8.762827928876504e-05
        },
        {
          "step": 6000,
          "loss": 7.87887183832936e-05
        }
      ],
      "oracle_good_bc": [
        {
          "step": 1,
          "loss": 0.020727509632706642
        },
        {
          "step": 1200,
          "loss": 7.970852311700583e-05
        },
        {
          "step": 2400,
          "loss": 8.534642984159291e-05
        },
        {
          "step": 3600,
          "loss": 7.406475924653932e-05
        },
        {
          "step": 4800,
          "loss": 7.176728831836954e-05
        },
        {
          "step": 6000,
          "loss": 6.738731462974101e-05
        }
      ]
    }
  }
]