[
  {
    "seed": 0,
    "bad_frac": 0.75,
    "transition_counts": {
      "positive": 160,
      "negative": 226,
      "unlabeled": 664,
      "unlabeled_hidden_good": 276,
      "unlabeled_hidden_bad": 388
    },
    "classifier": {
      "pos_prob_mean": 0.5023443698883057,
      "neg_prob_mean": 0.4978971481323242,
      "unlabeled_prob_mean": 0.5007656812667847,
      "unlabeled_hidden_good_prob_mean": 0.504770815372467,
      "unlabeled_hidden_bad_prob_mean": 0.49791669845581055,
      "labeled_accuracy": 0.7527654867256637
    },
    "histories": {
      "state_action_classifier": [
        {
          "step": 1,
          "loss": 1.3868541717529297
        },
        {
          "step": 2,
          "loss": 1.3824999332427979
        },
        {
          "step": 4,
          "loss": 1.3813210725784302
        },
        {
          "step": 6,
          "loss": 1.382611870765686
        },
        {
          "step": 8,
          "loss": 1.3811285495758057
        },
        {
          "step": 10,
          "loss": 1.3799182176589966
        }
      ],
      "bc_positive_prefix": [
        {
          "step": 1,
          "loss": 0.0002296027378179133
        },
        {
          "step": 2,
          "loss": 0.0001736200792947784
        },
        {
          "step": 4,
          "loss": 0.0001326716155745089
        },
        {
          "step": 6,
          "loss": 0.0001211986891576089
        },
        {
          "step": 8,
          "loss": 0.00010887135431403294
        },
        {
          "step": 10,
          "loss": 0.00011692718544509262
        }
      ],
      "bc_pos_unlabeled": [
        {
          "step": 1,
          "loss": 0.00290680886246264
        },
        {
          "step": 2,
          "loss": 0.0019754841923713684
        },
        {
          "step": 4,
          "loss": 0.0020883455872535706
        },
        {
          "step": 6,
          "loss": 0.0016611871542409062
        },
        {
          "step": 8,
          "loss": 0.0012382874265313148
        },
        {
          "step": 10,
          "loss": 0.001429057214409113
        }
      ],
      "bc_all": [
        {
          "step": 1,
          "loss": 0.0035986858420073986
        },
        {
          "step": 2,
          "loss": 0.004076005890965462
        },
        {
          "step": 4,
          "loss": 0.0036030905321240425
        },
        {
          "step": 6,
          "loss": 0.0014129329938441515
        },
        {
          "step": 8,
          "loss": 0.0020100059919059277
        },
        {
          "step": 10,
          "loss": 0.0015077039133757353
        }
      ],
      "weighted_bc_state_action": [
        {
          "step": 1,
          "loss": 0.002526623895391822
        },
        {
          "step": 2,
          "loss": 0.0027384564746171236
        },
        {
          "step": 4,
          "loss": 0.002655182033777237
        },
        {
          "step": 6,
          "loss": 0.0020347642712295055
        },
        {
          "step": 8,
          "loss": 0.0017468540463596582
        },
        {
          "step": 10,
          "loss": 0.0015959232114255428
        }
      ],
      "oracle_good_bc": [
        {
          "step": 1,
          "loss": 0.0019325838657096028
        },
        {
          "step": 2,
          "loss": 0.0018224511295557022
        },
        {
          "step": 4,
          "loss": 0.0012668415438383818
        },
        {
          "step": 6,
          "loss": 0.0011220979504287243
        },
        {
          "step": 8,
          "loss": 0.0008381698280572891
        },
        {
          "step": 10,
          "loss": 0.0006401488790288568
        }
      ]
    }
  }
]